sorting/__init__.py
sorting/bubble_sort.py
sorting/insertion_sort.py
sorting/quick_sort.py
sorting/selection_sort.py
sorting_anton/__init__.py
sorting_anton/bubble_sort.py
sorting_anton/insertion_sort.py
sorting_anton/quick_sort.py
sorting_anton/selection_sort.py
sorting_anton-0.2.dist-info/METADATA
sorting_anton-0.2.dist-info/WHEEL
sorting_anton-0.2.dist-info/top_level.txt
sorting_anton-0.2.dist-info/RECORD
