Metadata-Version: 2.1
Name: sorting-anton
Version: 0.2
Summary: This package lets you sort lists using Bubble Sort, Quick Sort, Insertion Sort and Selection Sort
Home-page: UNKNOWN
Author: Anton Benet
Author-email: abenet@rbi.com
License: MIT
Keywords: sorting_anton quick insert bubble selection
Platform: UNKNOWN
